oven_tensor/__init__.py
oven_tensor/cli.py
oven_tensor/kernels/__init__.py
oven_tensor/kernels/binary_ops.py
oven_tensor/kernels/dot_ops.py
oven_tensor/kernels/unary_ops.py
oven_tensor-0.1.1.dist-info/licenses/LICENSE
oven_tensor-0.1.1.dist-info/METADATA
oven_tensor-0.1.1.dist-info/WHEEL
oven_tensor-0.1.1.dist-info/entry_points.txt
oven_tensor-0.1.1.dist-info/top_level.txt
oven_tensor-0.1.1.dist-info/RECORD
