Metadata-Version: 2.4
Name: oven-tensor
Version: 0.1.1
Summary: PyTorch-style tensor operations with CUDA kernels compiled by oven-compiler
Author-email: Sinjin Jeong <sjjeong94@gmail.com>
License-Expression: MIT
Project-URL: Homepage, https://github.com/yourusername/oven-tensor
Project-URL: Bug Reports, https://github.com/yourusername/oven-tensor/issues
Project-URL: Source, https://github.com/yourusername/oven-tensor
Keywords: pytorch,cuda,gpu,tensor,machine-learning,deep-learning,oven
Classifier: Development Status :: 3 - Alpha
Classifier: Intended Audience :: Developers
Classifier: Intended Audience :: Science/Research
Classifier: Operating System :: OS Independent
Classifier: Programming Language :: Python :: 3
Classifier: Programming Language :: Python :: 3.7
Classifier: Programming Language :: Python :: 3.8
Classifier: Programming Language :: Python :: 3.9
Classifier: Programming Language :: Python :: 3.10
Classifier: Programming Language :: Python :: 3.11
Classifier: Topic :: Scientific/Engineering :: Artificial Intelligence
Classifier: Topic :: Software Development :: Libraries :: Python Modules
Requires-Python: >=3.7
License-File: LICENSE
Requires-Dist: numpy<2.0,>=1.19.0
Requires-Dist: pycuda>=2021.1
Requires-Dist: oven-compiler>=0.1.0
Provides-Extra: dev
Requires-Dist: pytest>=6.0; extra == "dev"
Requires-Dist: pytest-cov; extra == "dev"
Requires-Dist: black; extra == "dev"
Requires-Dist: flake8; extra == "dev"
Dynamic: license-file
